vpnfeedbacker/__init__.py
vpnfeedbacker/main.py
vpnfeedbacker/prompts.py
vpnfeedbacker-2025.12.21102332.dist-info/METADATA
vpnfeedbacker-2025.12.21102332.dist-info/WHEEL
vpnfeedbacker-2025.12.21102332.dist-info/top_level.txt
vpnfeedbacker-2025.12.21102332.dist-info/RECORD
