Metadata-Version: 2.4
Name: vpnfeedbacker
Version: 2025.12.21102332
Summary: A new package that simplifies and structures user feedback or descriptions about VPN sign-up experiences. It takes text input from users describing their sign-up process with a VPN service, such as ea
Author-email: vpnfeedbacker <hi@eugene.plus>
License: MIT
Project-URL: Homepage, https://github.com/chigwell/vpnfeedbacker
Requires-Python: >=3.9
Requires-Dist: langchain-llm7>=0.0.0
Requires-Dist: llmatch-messages>=0.0.0
Requires-Dist: langchain-core>=0.3.0
